hikyong/__init__.py
hikyong-0.0.1.dist-info/METADATA
hikyong-0.0.1.dist-info/WHEEL
hikyong-0.0.1.dist-info/top_level.txt
hikyong-0.0.1.dist-info/RECORD
